{
  "name": "intro",
  "routes": {
    "main": {
      "title": "Welcome",
      "icon": "home",
      "path": "/",
      "cover": {
        "image": "cover.r.png",
        "opacity": 0.5,
        "navigation": true,
        "title": "More than Learning",
        "subtitle": "Grow Your Tech Skills With Programming Challenges And Earn Experience Points",
        "type": "default",
        "primaryActionTitle": "Start Your Learning Journey"
      },
      "components": {
        "intro": {
          "source": "summary",
          "text": "local://intro",
          "image": "logo.png",
          "textColor": "#37474F"
        }
      }
    }
  }
}
